<?xml version="1.0" encoding="UTF-8" standalone="yes"?>
<apcg id="3_0" ctg="3" xmlns="http://webspace.ulbsibiu.ro/ciprian.radu/research/noc/application_mapping/unified_framework/schema/apcg">
    <core uid="0" id="44">
        <task id="0" execTime="1.0E-6" power="0.17"/>
    </core>
    <core uid="1" id="14">
        <task id="3" execTime="1.0E-5" power="2.5"/>
    </core>
    <core uid="2" id="15">
        <task id="2" execTime="0.0031" power="0.075"/>
    </core>
    <core uid="3" id="21">
        <task id="1" execTime="4.6E-4" power="16.0"/>
    </core>
</apcg>
